{"node":{"comments_disabled":false,"__typename":"GraphImage","id":"2703390540039142564","edge_media_to_caption":{"edges":[{"node":{"text":"\u0623\u0648\u0645\u0628\u0631\u064a \u0623\u0634\u0642\u0631 \u0648\u0639\u0633\u0644\u064a\ud83d\udcab\n\u062d\u0628\u064a\u062a\u0648\u0627 \u0627\u0644\u0644\u0648\u0646 \u0648\u0627\u0644\u062a\u063a\u064a\u064a\u0631\u061f\u061f\nGolden beauty salon\ud83c\udf80\n@lakmecolour\n@lakme\n#\u0627\u0648\u0645\u0628\u0631\u064a #\u0627\u0648\u0645\u0628\u0631\u064a_\u0645\u0644\u0648\u0646_\u0627\u0644\u0627\u0634\u0642\u0631_\u0648\u0627\u0644\u0639\u0633\u0644\u064a #\u0635\u0628\u063a\u0629_\u0634\u0639\u0631 #newlook#lakmecosmetics\n#lakmecolour"}}]},"shortcode":"CWEX198Lzyk","edge_media_to_comment":{"count":0},"taken_at_timestamp":1636489287,"dimensions":{"height":1080,"width":1080},"display_url":"https://scontent-lcy1-1.cdninstagram.com/v/t51.2885-15/254156071_1899968123506163_8465090602545219942_n.jpg?stp=dst-jpg_e35_s1080x1080&_nc_ht=scontent-lcy1-1.cdninstagram.com&_nc_cat=111&_nc_ohc=nvyROwXIQSgAX_XMeTF&edm=AA0rjkIBAAAA&ccb=7-5&oh=00_AT9CoVQBYEEUogKZ0QFhWAFF9RwuBU7pM3dzGOxJFL2pvQ&oe=62FAA850&_nc_sid=d997c6","edge_liked_by":{"count":17},"edge_media_preview_like":{"count":17},"owner":{"id":"49293361592"},"thumbnail_src":"https://scontent-lcy1-1.cdninstagram.com/v/t51.2885-15/254156071_1899968123506163_8465090602545219942_n.jpg?stp=dst-jpg_e35_s640x640_sh0.08&_nc_ht=scontent-lcy1-1.cdninstagram.com&_nc_cat=111&_nc_ohc=nvyROwXIQSgAX_XMeTF&edm=AA0rjkIBAAAA&ccb=7-5&oh=00_AT_8lpeouWzYNJxOWZRdLirO7GMghs-r-vY9f5PKQqSj4Q&oe=62FAA850&_nc_sid=d997c6","thumbnail_resources":[{"src":"https://scontent-lcy1-1.cdninstagram.com/v/t51.2885-15/254156071_1899968123506163_8465090602545219942_n.jpg?stp=dst-jpg_e35_s150x150&_nc_ht=scontent-lcy1-1.cdninstagram.com&_nc_cat=111&_nc_ohc=nvyROwXIQSgAX_XMeTF&edm=AA0rjkIBAAAA&ccb=7-5&oh=00_AT_Ele-84cmnAccW8EGBeOGqYJ393M1ebfkF6lXoXT0IEw&oe=62FAA850&_nc_sid=d997c6","config_width":150,"config_height":150},{"src":"https://scontent-lcy1-1.cdninstagram.com/v/t51.2885-15/254156071_1899968123506163_8465090602545219942_n.jpg?stp=dst-jpg_e35_s240x240&_nc_ht=scontent-lcy1-1.cdninstagram.com&_nc_cat=111&_nc_ohc=nvyROwXIQSgAX_XMeTF&edm=AA0rjkIBAAAA&ccb=7-5&oh=00_AT9wAKkZ8tGeeE9HlpWP1zKJWZIpxu0Z301J7UJjN8EYMg&oe=62FAA850&_nc_sid=d997c6","config_width":240,"config_height":240},{"src":"https://scontent-lcy1-1.cdninstagram.com/v/t51.2885-15/254156071_1899968123506163_8465090602545219942_n.jpg?stp=dst-jpg_e35_s320x320&_nc_ht=scontent-lcy1-1.cdninstagram.com&_nc_cat=111&_nc_ohc=nvyROwXIQSgAX_XMeTF&edm=AA0rjkIBAAAA&ccb=7-5&oh=00_AT8SYa8QvmvRwyJ5i6JDt2WBOmG4B4t6K7yjfzx-Swtdfg&oe=62FAA850&_nc_sid=d997c6","config_width":320,"config_height":320},{"src":"https://scontent-lcy1-1.cdninstagram.com/v/t51.2885-15/254156071_1899968123506163_8465090602545219942_n.jpg?stp=dst-jpg_e35_s480x480&_nc_ht=scontent-lcy1-1.cdninstagram.com&_nc_cat=111&_nc_ohc=nvyROwXIQSgAX_XMeTF&edm=AA0rjkIBAAAA&ccb=7-5&oh=00_AT_MPaOthibQclpys1Fsl9bt6j9B5qlHTY7lfskKgaPnFw&oe=62FAA850&_nc_sid=d997c6","config_width":480,"config_height":480},{"src":"https://scontent-lcy1-1.cdninstagram.com/v/t51.2885-15/254156071_1899968123506163_8465090602545219942_n.jpg?stp=dst-jpg_e35_s640x640_sh0.08&_nc_ht=scontent-lcy1-1.cdninstagram.com&_nc_cat=111&_nc_ohc=nvyROwXIQSgAX_XMeTF&edm=AA0rjkIBAAAA&ccb=7-5&oh=00_AT_8lpeouWzYNJxOWZRdLirO7GMghs-r-vY9f5PKQqSj4Q&oe=62FAA850&_nc_sid=d997c6","config_width":640,"config_height":640}],"is_video":false,"accessibility_caption":null},"instaloader":{"version":"4.9.1","node_type":"Post"}}