{"node":{"comments_disabled":false,"__typename":"GraphImage","id":"2135416840627764254","edge_media_to_caption":{"edges":[{"node":{"text":"#durgapuja #durgapujainusa #durgamaa #saree #sareelover #sareedraping #sareelovers #sareeindia #sareestyle #sareeblouse #makeup #makeuplover #makeupaddict #makeupjunkie #beautymakeup #beautyjunkie #beautyaddict #beautyproducts #beautycommunity #beautyblog #beautygram #lakmecosmetics #lakmeabsolute #lakmeproducts"}}]},"shortcode":"B2ihk15ATwe","edge_media_to_comment":{"count":0},"taken_at_timestamp":1568781546,"dimensions":{"height":750,"width":750},"display_url":"https://scontent-lcy1-1.cdninstagram.com/v/t51.2885-15/69091395_221087058876299_1425084990722757547_n.jpg?stp=dst-jpg_e35&_nc_ht=scontent-lcy1-1.cdninstagram.com&_nc_cat=111&_nc_ohc=YPKpNQMLtrIAX92EREe&edm=AA0rjkIBAAAA&ccb=7-5&oh=00_AT8lKPdU9O_gxqZwQlWSxzzAfmBvDVRNKWHi_vVZ-ACwwA&oe=62F90F2E&_nc_sid=d997c6","edge_liked_by":{"count":33},"edge_media_preview_like":{"count":33},"owner":{"id":"221105502"},"thumbnail_src":"https://scontent-lcy1-1.cdninstagram.com/v/t51.2885-15/69091395_221087058876299_1425084990722757547_n.jpg?stp=dst-jpg_e35_s640x640_sh0.08&_nc_ht=scontent-lcy1-1.cdninstagram.com&_nc_cat=111&_nc_ohc=YPKpNQMLtrIAX92EREe&edm=AA0rjkIBAAAA&ccb=7-5&oh=00_AT-ILlm4jeS9pZ5qqDmsLcWlhoQJk_bsBz4TyWafKO7vJw&oe=62F90F2E&_nc_sid=d997c6","thumbnail_resources":[{"src":"https://scontent-lcy1-1.cdninstagram.com/v/t51.2885-15/69091395_221087058876299_1425084990722757547_n.jpg?stp=dst-jpg_e35_s150x150&_nc_ht=scontent-lcy1-1.cdninstagram.com&_nc_cat=111&_nc_ohc=YPKpNQMLtrIAX92EREe&edm=AA0rjkIBAAAA&ccb=7-5&oh=00_AT814glQOqLuR_uDfpI7oaespO4iR3EMjyBIyZSwTzHrrA&oe=62F90F2E&_nc_sid=d997c6","config_width":150,"config_height":150},{"src":"https://scontent-lcy1-1.cdninstagram.com/v/t51.2885-15/69091395_221087058876299_1425084990722757547_n.jpg?stp=dst-jpg_e35_s240x240&_nc_ht=scontent-lcy1-1.cdninstagram.com&_nc_cat=111&_nc_ohc=YPKpNQMLtrIAX92EREe&edm=AA0rjkIBAAAA&ccb=7-5&oh=00_AT-FRayWVWfxCV_ZBp-culSwXnCR6V7Bam_LiPQ2zwL2Ug&oe=62F90F2E&_nc_sid=d997c6","config_width":240,"config_height":240},{"src":"https://scontent-lcy1-1.cdninstagram.com/v/t51.2885-15/69091395_221087058876299_1425084990722757547_n.jpg?stp=dst-jpg_e35_s320x320&_nc_ht=scontent-lcy1-1.cdninstagram.com&_nc_cat=111&_nc_ohc=YPKpNQMLtrIAX92EREe&edm=AA0rjkIBAAAA&ccb=7-5&oh=00_AT_iNYbj8MSbtH8PZ_OokTn5KAiB7ZPDHy6TACLeCHIFdg&oe=62F90F2E&_nc_sid=d997c6","config_width":320,"config_height":320},{"src":"https://scontent-lcy1-1.cdninstagram.com/v/t51.2885-15/69091395_221087058876299_1425084990722757547_n.jpg?stp=dst-jpg_e35_s480x480&_nc_ht=scontent-lcy1-1.cdninstagram.com&_nc_cat=111&_nc_ohc=YPKpNQMLtrIAX92EREe&edm=AA0rjkIBAAAA&ccb=7-5&oh=00_AT_-oV9oLFpwvR4Oo9c7Vc9w6O3Q61Ukk4opEAzejdnXmQ&oe=62F90F2E&_nc_sid=d997c6","config_width":480,"config_height":480},{"src":"https://scontent-lcy1-1.cdninstagram.com/v/t51.2885-15/69091395_221087058876299_1425084990722757547_n.jpg?stp=dst-jpg_e35_s640x640_sh0.08&_nc_ht=scontent-lcy1-1.cdninstagram.com&_nc_cat=111&_nc_ohc=YPKpNQMLtrIAX92EREe&edm=AA0rjkIBAAAA&ccb=7-5&oh=00_AT-ILlm4jeS9pZ5qqDmsLcWlhoQJk_bsBz4TyWafKO7vJw&oe=62F90F2E&_nc_sid=d997c6","config_width":640,"config_height":640}],"is_video":false,"accessibility_caption":null},"instaloader":{"version":"4.9.1","node_type":"Post"}}